{
  "name": "SWAP",
  "timestamp": "2020-08-25T15:41:29.665Z",
  "version": {
    "major": 1,
    "minor": 3,
    "patch": 1
  },
  "tags": {},
  "logoURI": "/images/coins/weth.png",
  "keywords": ["uniswap", "default"],
  "tokens": [
    {
      "name": "Wrapped ETH",
      "symbol": "WETH",
      "address": "0xc02aaa39b223fe8d0a0e5c4f27ead9083c756cc2",
      "chainId": 1,
      "decimals": 18
    },
    {
      "name": "4Chan 2.0",
      "symbol": "4Chan2.0",
      "address": "0x54dc15C741196d268eb17858B63B1277cE439581",
      "chainId": 1,
      "decimals": 9,
      "logo": "/images/192x192_App_Icon.png"
    }
  ]
}
